e_lims/__init__.py
e_lims/e_lims.py
e_lims/py.typed
e_lims-0.0.4.dist-info/LICENSE
e_lims-0.0.4.dist-info/WHEEL
e_lims-0.0.4.dist-info/METADATA
e_lims-0.0.4.dist-info/RECORD
