Metadata-Version: 2.1
Name: e-lims
Version: 0.0.4
Summary: E-lims Cookiecutter Template.
License: MIT
Author: Fabien Meyer
Author-email: fabien-meyer@outlook.com
Requires-Python: >=3.10,<4.0
Classifier: License :: OSI Approved :: MIT License
Classifier: Programming Language :: Python :: 3
Classifier: Programming Language :: Python :: 3.10
Classifier: Programming Language :: Python :: 3.11
Provides-Extra: doc
Provides-Extra: tests
Requires-Dist: Sphinx (>=5.3.0,<6.0.0); extra == "doc"
Requires-Dist: bump2version (>=1.0.1,<2.0.0)
Requires-Dist: pytest (>=7.1.3,<8.0.0); extra == "tests"
Requires-Dist: pytest-cookies (>=0.6.1,<0.7.0); extra == "tests"
Requires-Dist: pytest-cov (>=4.0.0,<5.0.0); extra == "tests"
Requires-Dist: sphinx-autodoc-typehints (>=1.19.4,<2.0.0); extra == "doc"
Requires-Dist: sphinx-rtd-theme (>=1.0.0,<2.0.0); extra == "doc"
Requires-Dist: sphinxcontrib-mermaid (>=0.7.1,<0.8.0); extra == "doc"
Requires-Dist: typing_extensions (>=4.4.0,<5.0.0)
